houses_pipeline/VERSION
houses_pipeline/__init__.py
houses_pipeline/constants.py
houses_pipeline/transformers.py
houses_pipeline/config/__init__.py
houses_pipeline/config/config.py
houses_pipeline/config/logging_configuration.py
houses_pipeline/fetch/.gitkeep
houses_pipeline/fetch/fetch_dataset.sh
houses_pipeline/modelling/__init__.py
houses_pipeline/modelling/train_lasso.py
houses_pipeline/preprocess/__init__.py
houses_pipeline/preprocess/__main__.py
houses_pipeline/tests/__init__.py
houses_pipeline/tests/test_transformers.py
houses_pipeline-0.0.1.dist-info/LICENSE
houses_pipeline-0.0.1.dist-info/METADATA
houses_pipeline-0.0.1.dist-info/WHEEL
houses_pipeline-0.0.1.dist-info/top_level.txt
houses_pipeline-0.0.1.dist-info/RECORD
