Metadata-Version: 2.1
Name: houses-pipeline
Version: 0.0.1
Summary: Houses pipeline for preprocessing and training a model
Home-page: https://github.com/nshahpazov/houses-ds-project
Author: Nikola Shahpazov
Author-email: nshahpazov@gmail.com
License: BSD 3
Classifier: License :: OSI Approved :: MIT License
Classifier: Programming Language :: Python
Classifier: Programming Language :: Python :: 3
Classifier: Programming Language :: Python :: 3.6
Classifier: Programming Language :: Python :: 3.7
Classifier: Programming Language :: Python :: 3.8
Classifier: Programming Language :: Python :: Implementation :: CPython
Classifier: Programming Language :: Python :: Implementation :: PyPy
Requires-Python: >=3.9.2
License-File: LICENSE
Provides-Extra: dev
Requires-Dist: pytest (>=7.1.2) ; extra == 'dev'
